synarixaggregator/IERC20.py
synarixaggregator/SynarixAC_F.py
synarixaggregator/SynarixAM.py
synarixaggregator/W3Utils.py
synarixaggregator/__init__.py
synarixaggregator/core_abis.py
synarixaggregator/core_chains.py
synarixaggregator/core_settings.py
SynarixAggregator-0.0.2.dist-info/LICENSE
SynarixAggregator-0.0.2.dist-info/METADATA
SynarixAggregator-0.0.2.dist-info/WHEEL
SynarixAggregator-0.0.2.dist-info/top_level.txt
SynarixAggregator-0.0.2.dist-info/RECORD
